pcsFilter/__init__.py
pcsFilter/app.py
pcsFilter/cli.py
pcsFilter/file_handling/__init__.py
pcsFilter/file_handling/abstract_file_handler.py
pcsFilter/file_handling/existing_file.py
pcsFilter/file_handling/file_finder.py
pcsFilter/file_handling/non_existing_file.py
pcsFilter/quality_handler.py
pcsFilter/setup_handler.py
pcsFilter/tools/__init__.py
pcsFilter/tools/black.py
pcsFilter/tools/blue.py
pcsFilter/tools/flake8.py
pcsFilter/tools/isort.py
pcsFilter/tools/radon.py
pcsfilter-1.0.4.dist-info/LICENSE
pcsfilter-1.0.4.dist-info/METADATA
pcsfilter-1.0.4.dist-info/WHEEL
pcsfilter-1.0.4.dist-info/entry_points.txt
pcsfilter-1.0.4.dist-info/RECORD
