Metadata-Version: 2.1
Name: pcsFilter
Version: 1.0.4
Summary: 
Author: Sasha Bondarev
Author-email: github.pcsfilter@gmail.com
Requires-Python: >=3.7,<4.0
Classifier: Programming Language :: Python :: 3
Classifier: Programming Language :: Python :: 3.7
Classifier: Programming Language :: Python :: 3.8
Classifier: Programming Language :: Python :: 3.9
Classifier: Programming Language :: Python :: 3.10
Classifier: Programming Language :: Python :: 3.11
Requires-Dist: ConfigUpdater (>=3.0.0,<3.1.0)
Requires-Dist: blue (>=0.9.0,<0.10.0)
Requires-Dist: click (>=8.0.0,<8.1.0)
Requires-Dist: flake8 (>=3.8,<5.0.0)
Requires-Dist: isort (>=5.10.0,<5.11.0)
Requires-Dist: pytest (>=7.2.0,<7.3.0)
Requires-Dist: radon (>=6.0.1,<6.1.0)
Requires-Dist: wheel (>=0.38.1)
